<?xml version="1.0" encoding="utf-8" ?>
<dwsync>
<file name="abbr.htm" server="ftp.pgsitalia.org" local="128981064620000000" remote="129157929000000000" />
<file name="acronym.htm" server="ftp.pgsitalia.org" local="128981064620000000" remote="129157929000000000" />
<file name="attributes.htm" server="ftp.pgsitalia.org" local="128981064620000000" remote="129157929000000000" />
<file name="cite.htm" server="ftp.pgsitalia.org" local="128981064620000000" remote="129157929000000000" />
<file name="del.htm" server="ftp.pgsitalia.org" local="128981064620000000" remote="129157929600000000" />
<file name="editor_plugin.js" server="ftp.pgsitalia.org" local="128981064600000000" remote="129157929600000000" />
<file name="editor_plugin_src.js" server="ftp.pgsitalia.org" local="128981064600000000" remote="129157929600000000" />
<file name="ins.htm" server="ftp.pgsitalia.org" local="128981064620000000" remote="129157929600000000" />
<file name="abbr.htm" server="ftp.stemurasolutions.com/stemurasolutions.com/social/" local="128981064620000000" remote="129381118200000000" />
<file name="acronym.htm" server="ftp.stemurasolutions.com/stemurasolutions.com/social/" local="128981064620000000" remote="129381118200000000" />
<file name="attributes.htm" server="ftp.stemurasolutions.com/stemurasolutions.com/social/" local="128981064620000000" remote="129381118200000000" />
<file name="cite.htm" server="ftp.stemurasolutions.com/stemurasolutions.com/social/" local="128981064620000000" remote="129381118200000000" />
<file name="del.htm" server="ftp.stemurasolutions.com/stemurasolutions.com/social/" local="128981064620000000" remote="129381118200000000" />
<file name="editor_plugin.js" server="ftp.stemurasolutions.com/stemurasolutions.com/social/" local="128981064600000000" remote="129381118200000000" />
<file name="editor_plugin_src.js" server="ftp.stemurasolutions.com/stemurasolutions.com/social/" local="128981064600000000" remote="129381118200000000" />
<file name="ins.htm" server="ftp.stemurasolutions.com/stemurasolutions.com/social/" local="128981064620000000" remote="129381118200000000" />
</dwsync>